steel/__init__.py
steel/base.py
steel/fields/__init__.py
steel/fields/base.py
steel/fields/bytes.py
steel/fields/datetime.py
steel/fields/enum.py
steel/fields/numbers.py
steel/fields/text.py
steel/py.typed
steel/types.py
steel-0.5.dist-info/licenses/LICENSE
steel-0.5.dist-info/WHEEL
steel-0.5.dist-info/METADATA
steel-0.5.dist-info/RECORD
