Metadata-Version: 2.4
Name: steel
Version: 0.5
Summary: A Python framework for describing, reading and writing binary file formats
Author: Ginger Hawthorne
Author-email: Ginger Hawthorne <gulopine@gmail.com>
License-Expression: BSD-3-Clause-No-Military-License
License-File: LICENSE
Classifier: Development Status :: 3 - Alpha
Classifier: Intended Audience :: Developers
Classifier: License :: OSI Approved :: BSD License
Classifier: Operating System :: OS Independent
Classifier: Programming Language :: Python :: 3
Classifier: Topic :: Software Development :: Libraries :: Application Frameworks
Classifier: Topic :: System :: Filesystems
Requires-Python: >=3.13
Project-URL: Homepage, https://importsteel.org/
Project-URL: Issues, https://github.com/gulopine/steel/issues
